<?xml version='1.0' encoding='utf-8'?>
<TextureAtlas imagePath="GuballSustado.png">
	
	
	<SubTexture name="down0000" x="502.79999999999995" y="911.4" width="273.59999999999997" height="246.6" frameX="-4.8" frameY="-85.2" frameWidth="289.2" frameHeight="347.4" />
	<SubTexture name="down0001" x="502.79999999999995" y="911.4" width="273.59999999999997" height="246.6" frameX="-4.8" frameY="-85.2" frameWidth="289.2" frameHeight="347.4" />
	<SubTexture name="down0002" x="733.8" y="606.6" width="265.2" height="246.6" frameX="-11.4" frameY="-85.2" frameWidth="289.2" frameHeight="347.4" />
	<SubTexture name="down0003" x="733.8" y="606.6" width="265.2" height="246.6" frameX="-11.4" frameY="-85.2" frameWidth="289.2" frameHeight="347.4" />
	<SubTexture name="down0004" x="776.4" y="911.4" width="265.2" height="246.6" frameX="-11.4" frameY="-85.2" frameWidth="289.2" frameHeight="347.4" />
	<SubTexture name="down0005" x="776.4" y="911.4" width="265.2" height="246.6" frameX="-11.4" frameY="-85.2" frameWidth="289.2" frameHeight="347.4" />
	<SubTexture name="down0006" x="1041.6" y="911.4" width="264.59999999999997" height="246.6" frameX="-9.6" frameY="-83.39999999999999" frameWidth="289.2" frameHeight="347.4" />
	<SubTexture name="down0007" x="1041.6" y="911.4" width="264.59999999999997" height="246.6" frameX="-9.6" frameY="-83.39999999999999" frameWidth="289.2" frameHeight="347.4" />
	<SubTexture name="down0008" x="229.2" y="911.4" width="273.59999999999997" height="248.39999999999998" frameX="-4.8" frameY="-83.39999999999999" frameWidth="289.2" frameHeight="347.4" />
	<SubTexture name="down0009" x="229.2" y="911.4" width="273.59999999999997" height="248.39999999999998" frameX="-4.8" frameY="-83.39999999999999" frameWidth="289.2" frameHeight="347.4" />
	<SubTexture name="down0010" x="258.59999999999997" y="309.0" width="262.8" height="271.8" frameX="-15.6" frameY="-58.8" frameWidth="289.2" frameHeight="347.4" />
	<SubTexture name="down0011" x="258.59999999999997" y="309.0" width="262.8" height="271.8" frameX="-15.6" frameY="-58.8" frameWidth="289.2" frameHeight="347.4" />
	<SubTexture name="down0012" x="211.2" y="1211.3999999999999" width="223.79999999999998" height="276.0" frameX="-50.4" frameY="-52.199999999999996" frameWidth="289.2" frameHeight="347.4" />
	<SubTexture name="down0013" x="211.2" y="1211.3999999999999" width="223.79999999999998" height="276.0" frameX="-50.4" frameY="-52.199999999999996" frameWidth="289.2" frameHeight="347.4" />
	<SubTexture name="down0014" x="0.0" y="1523.3999999999999" width="196.2" height="303.59999999999997" frameX="-73.8" frameY="-27.0" frameWidth="289.2" frameHeight="347.4" />
	<SubTexture name="idle0000" x="1835.3999999999999" y="0.0" width="193.2" height="318.0" frameX="-13.799999999999999" frameY="-28.2" frameWidth="257.4" frameHeight="361.2" />
	<SubTexture name="idle0001" x="1835.3999999999999" y="0.0" width="193.2" height="318.0" frameX="-13.799999999999999" frameY="-28.2" frameWidth="257.4" frameHeight="361.2" />
	<SubTexture name="idle0002" x="1642.2" y="640.8" width="192.6" height="320.4" frameX="-14.399999999999999" frameY="-25.8" frameWidth="257.4" frameHeight="361.2" />
	<SubTexture name="idle0003" x="1642.2" y="640.8" width="192.6" height="320.4" frameX="-14.399999999999999" frameY="-25.8" frameWidth="257.4" frameHeight="361.2" />
	<SubTexture name="idle0004" x="1642.2" y="320.4" width="193.2" height="320.4" frameX="-13.799999999999999" frameY="-25.8" frameWidth="257.4" frameHeight="361.2" />
	<SubTexture name="idle0005" x="1642.2" y="320.4" width="193.2" height="320.4" frameX="-13.799999999999999" frameY="-25.8" frameWidth="257.4" frameHeight="361.2" />
	<SubTexture name="idle0006" x="1642.2" y="0.0" width="193.2" height="320.4" frameX="-13.799999999999999" frameY="-25.8" frameWidth="257.4" frameHeight="361.2" />
	<SubTexture name="idle0007" x="1642.2" y="0.0" width="193.2" height="320.4" frameX="-13.799999999999999" frameY="-25.8" frameWidth="257.4" frameHeight="361.2" />
	<SubTexture name="idle0008" x="1642.2" y="961.1999999999999" width="192.6" height="320.4" frameX="-14.399999999999999" frameY="-25.8" frameWidth="257.4" frameHeight="361.2" />
	<SubTexture name="idle0009" x="1642.2" y="961.1999999999999" width="192.6" height="320.4" frameX="-14.399999999999999" frameY="-25.8" frameWidth="257.4" frameHeight="361.2" />
	<SubTexture name="left0000" x="0.0" y="309.0" width="258.59999999999997" height="297.59999999999997" frameX="-1.7999999999999998" frameY="-18.0" frameWidth="355.8" frameHeight="334.2" />
	<SubTexture name="left0001" x="0.0" y="309.0" width="258.59999999999997" height="297.59999999999997" frameX="-1.7999999999999998" frameY="-18.0" frameWidth="355.8" frameHeight="334.2" />
	<SubTexture name="left0002" x="250.2" y="606.6" width="241.79999999999998" height="295.2" frameX="-16.8" frameY="-18.599999999999998" frameWidth="355.8" frameHeight="334.2" />
	<SubTexture name="left0003" x="250.2" y="606.6" width="241.79999999999998" height="295.2" frameX="-16.8" frameY="-18.599999999999998" frameWidth="355.8" frameHeight="334.2" />
	<SubTexture name="left0004" x="492.0" y="606.6" width="241.79999999999998" height="293.4" frameX="-16.8" frameY="-20.4" frameWidth="355.8" frameHeight="334.2" />
	<SubTexture name="left0005" x="492.0" y="606.6" width="241.79999999999998" height="293.4" frameX="-16.8" frameY="-20.4" frameWidth="355.8" frameHeight="334.2" />
	<SubTexture name="left0006" x="752.4" y="304.8" width="241.79999999999998" height="295.2" frameX="-16.8" frameY="-20.4" frameWidth="355.8" frameHeight="334.2" />
	<SubTexture name="left0007" x="752.4" y="304.8" width="241.79999999999998" height="295.2" frameX="-16.8" frameY="-20.4" frameWidth="355.8" frameHeight="334.2" />
	<SubTexture name="left0008" x="0.0" y="309.0" width="258.59999999999997" height="297.59999999999997" frameX="-1.7999999999999998" frameY="-18.0" frameWidth="355.8" frameHeight="334.2" />
	<SubTexture name="left0009" x="0.0" y="309.0" width="258.59999999999997" height="297.59999999999997" frameX="-1.7999999999999998" frameY="-18.0" frameWidth="355.8" frameHeight="334.2" />
	<SubTexture name="left0010" x="0.0" y="911.4" width="229.2" height="300.0" frameX="-29.4" frameY="-20.4" frameWidth="355.8" frameHeight="334.2" />
	<SubTexture name="left0011" x="0.0" y="911.4" width="229.2" height="300.0" frameX="-29.4" frameY="-20.4" frameWidth="355.8" frameHeight="334.2" />
	<SubTexture name="left0012" x="196.2" y="1523.3999999999999" width="183.6" height="297.59999999999997" frameX="-75.0" frameY="-20.4" frameWidth="355.8" frameHeight="334.2" />
	<SubTexture name="left0013" x="196.2" y="1523.3999999999999" width="183.6" height="297.59999999999997" frameX="-75.0" frameY="-20.4" frameWidth="355.8" frameHeight="334.2" />
	<SubTexture name="left0014" x="1835.3999999999999" y="639.6" width="187.79999999999998" height="307.8" frameX="-135.6" frameY="-12.6" frameWidth="355.8" frameHeight="334.2" />
	<SubTexture name="right0000" x="0.0" y="606.6" width="250.2" height="304.8" frameX="-26.4" frameY="-34.8" frameWidth="308.4" frameHeight="349.8" />
	<SubTexture name="right0001" x="0.0" y="606.6" width="250.2" height="304.8" frameX="-26.4" frameY="-34.8" frameWidth="308.4" frameHeight="349.8" />
	<SubTexture name="right0002" x="502.79999999999995" y="0.0" width="249.6" height="309.0" frameX="-31.2" frameY="-30.599999999999998" frameWidth="308.4" frameHeight="349.8" />
	<SubTexture name="right0003" x="502.79999999999995" y="0.0" width="249.6" height="309.0" frameX="-31.2" frameY="-30.599999999999998" frameWidth="308.4" frameHeight="349.8" />
	<SubTexture name="right0004" x="0.0" y="0.0" width="252.6" height="309.0" frameX="-30.599999999999998" frameY="-30.599999999999998" frameWidth="308.4" frameHeight="349.8" />
	<SubTexture name="right0005" x="0.0" y="0.0" width="252.6" height="309.0" frameX="-30.599999999999998" frameY="-30.599999999999998" frameWidth="308.4" frameHeight="349.8" />
	<SubTexture name="right0006" x="752.4" y="0.0" width="250.79999999999998" height="304.8" frameX="-27.0" frameY="-34.8" frameWidth="308.4" frameHeight="349.8" />
	<SubTexture name="right0007" x="752.4" y="0.0" width="250.79999999999998" height="304.8" frameX="-27.0" frameY="-34.8" frameWidth="308.4" frameHeight="349.8" />
	<SubTexture name="right0008" x="252.6" y="0.0" width="250.2" height="309.0" frameX="-30.599999999999998" frameY="-30.599999999999998" frameWidth="308.4" frameHeight="349.8" />
	<SubTexture name="right0009" x="252.6" y="0.0" width="250.2" height="309.0" frameX="-30.599999999999998" frameY="-30.599999999999998" frameWidth="308.4" frameHeight="349.8" />
	<SubTexture name="right0010" x="0.0" y="1211.3999999999999" width="211.2" height="312.0" frameX="-31.799999999999997" frameY="-28.799999999999997" frameWidth="308.4" frameHeight="349.8" />
	<SubTexture name="right0011" x="0.0" y="1211.3999999999999" width="211.2" height="312.0" frameX="-31.799999999999997" frameY="-28.799999999999997" frameWidth="308.4" frameHeight="349.8" />
	<SubTexture name="right0012" x="1835.3999999999999" y="318.0" width="188.4" height="321.59999999999997" frameX="-22.2" frameY="-19.2" frameWidth="308.4" frameHeight="349.8" />
	<SubTexture name="right0013" x="1835.3999999999999" y="318.0" width="188.4" height="321.59999999999997" frameX="-22.2" frameY="-19.2" frameWidth="308.4" frameHeight="349.8" />
	<SubTexture name="right0014" x="1835.3999999999999" y="947.4" width="177.0" height="321.0" frameX="-13.799999999999999" frameY="-19.8" frameWidth="308.4" frameHeight="349.8" />
	<SubTexture name="up0000" x="1221.6" y="345.59999999999997" width="209.4" height="336.0" frameX="-22.8" frameY="-16.8" frameWidth="285.0" frameHeight="363.59999999999997" />
	<SubTexture name="up0001" x="1221.6" y="345.59999999999997" width="209.4" height="336.0" frameX="-22.8" frameY="-16.8" frameWidth="285.0" frameHeight="363.59999999999997" />
	<SubTexture name="up0002" x="1221.6" y="0.0" width="216.0" height="345.59999999999997" frameX="-18.0" frameY="-7.199999999999999" frameWidth="285.0" frameHeight="363.59999999999997" />
	<SubTexture name="up0003" x="1221.6" y="0.0" width="216.0" height="345.59999999999997" frameX="-18.0" frameY="-7.199999999999999" frameWidth="285.0" frameHeight="363.59999999999997" />
	<SubTexture name="up0004" x="1003.1999999999999" y="345.59999999999997" width="217.2" height="345.59999999999997" frameX="-16.8" frameY="-7.199999999999999" frameWidth="285.0" frameHeight="363.59999999999997" />
	<SubTexture name="up0005" x="1003.1999999999999" y="345.59999999999997" width="217.2" height="345.59999999999997" frameX="-16.8" frameY="-7.199999999999999" frameWidth="285.0" frameHeight="363.59999999999997" />
	<SubTexture name="up0006" x="1003.1999999999999" y="0.0" width="218.4" height="345.59999999999997" frameX="-15.6" frameY="-7.199999999999999" frameWidth="285.0" frameHeight="363.59999999999997" />
	<SubTexture name="up0007" x="1003.1999999999999" y="0.0" width="218.4" height="345.59999999999997" frameX="-15.6" frameY="-7.199999999999999" frameWidth="285.0" frameHeight="363.59999999999997" />
	<SubTexture name="up0008" x="1221.6" y="345.59999999999997" width="209.4" height="336.0" frameX="-22.8" frameY="-16.8" frameWidth="285.0" frameHeight="363.59999999999997" />
	<SubTexture name="up0009" x="1221.6" y="345.59999999999997" width="209.4" height="336.0" frameX="-22.8" frameY="-16.8" frameWidth="285.0" frameHeight="363.59999999999997" />
	<SubTexture name="up0010" x="1437.6" y="0.0" width="204.6" height="327.0" frameX="-27.599999999999998" frameY="-23.4" frameWidth="285.0" frameHeight="363.59999999999997" />
	<SubTexture name="up0011" x="1437.6" y="0.0" width="204.6" height="327.0" frameX="-27.599999999999998" frameY="-23.4" frameWidth="285.0" frameHeight="363.59999999999997" />
	<SubTexture name="up0012" x="1437.6" y="327.0" width="194.4" height="321.0" frameX="-36.0" frameY="-29.4" frameWidth="285.0" frameHeight="363.59999999999997" />
	<SubTexture name="up0013" x="1437.6" y="327.0" width="194.4" height="321.0" frameX="-36.0" frameY="-29.4" frameWidth="285.0" frameHeight="363.59999999999997" />
	<SubTexture name="up0014" x="1437.6" y="648.0" width="189.6" height="328.8" frameX="-57.0" frameY="-21.599999999999998" frameWidth="285.0" frameHeight="363.59999999999997" />
</TextureAtlas>